Workbook
Name Slicer_Category: #N/A
Name Slicer_Product: #N/A
Name Slicer_Region: #N/A
Name Slicer_Salesperson: #N/A

Sheet dataset
A1: Date | B1: Daily trend | C1: Region | D1: Salesperson | E1: Product | F1: Category | G1: Quantity Sold | H1: Unit Price (NGN) | I1: Customer Name | J1: Gender | K1: Cost Price (NGN) | L1: total sales | M1: PROFIT | N1: PROFIT MARGIN | O1: COST PRICE | Q1: total number of transactions | T1: calculating for total cost
A2: 45789 | B2: =DAY(A2) -> 12 | C2: Lagos | D2: Bola | E2: Eggs | F2: Roots | G2: 36 | H2: 789 | I2: Customer_1 | J2: Male | K2: 700 | L2: =G2*H2 -> 28404 | M2: =dataset!$L2-T2 -> 3204 | N2: =dataset!$M2/dataset!$L2*100 -> 11.280101 | O2: =dataset!$K2*dataset!$G2 -> 25200 | P2: product with highest unit price | Q2: =COUNTA(H2:H801) -> 800 | T2: =dataset!$K2*dataset!$G2 -> 25200
A3: 45770 | B3: =DAY(A3) -> 23 | C3: Lagos | D3: Ngozi | E3: Soap | F3: Protein | G3: 23 | H3: 774 | I3: Customer_10 | J3: Female | K3: 700 | L3: =G3*H3 -> 17802 | M3: =dataset!$L3-T3 -> 1702 | N3: =dataset!$M3/dataset!$L3*100 -> 9.5607235 | O3: =dataset!$K3*dataset!$G3 -> 16100 | P3: =INDEX(E2:E801,MATCH(MAX(H2:H801),H2:H801,0)) -> Rice | T3: =dataset!$K3*dataset!$G3 -> 16100
A4: 45765 | B4: =DAY(A4) -> 18 | C4: Abuja | D4: John | E4: Plantain Chips | F4: Legumes | G4: 48 | H4: 2262 | I4: Customer_100 | J4: Male | K4: 2000 | L4: =G4*H4 -> 108576 | M4: =dataset!$L4-T4 -> 12576 | N4: =dataset!$M4/dataset!$L4*100 -> 11.58267 | O4: =dataset!$K4*dataset!$G4 -> 96000 | T4: =dataset!$K4*dataset!$G4 -> 96000
A5: 45749 | B5: =DAY(A5) -> 2 | C5: Abuja | D5: Ngozi | E5: Soap | F5: Grains | G5: 25 | H5: 2064 | I5: Customer_101 | J5: Male | K5: 1800 | L5: =G5*H5 -> 51600 | M5: =dataset!$L5-T5 -> 6600 | N5: =dataset!$M5/dataset!$L5*100 -> 12.790698 | O5: =dataset!$K5*dataset!$G5 -> 45000 | T5: =dataset!$K5*dataset!$G5 -> 45000
A6: 45835 | B6: =DAY(A6) -> 27 | C6: Port Harcourt | D6: Bola | E6: Bread | F6: Beverages | G6: 5 | H6: 2989 | I6: Customer_102 | J6: Male | K6: 2400 | L6: =G6*H6 -> 14945 | M6: =dataset!$L6-T6 -> 2945 | N6: =dataset!$M6/dataset!$L6*100 -> 19.705587 | O6: =dataset!$K6*dataset!$G6 -> 12000 | T6: =dataset!$K6*dataset!$G6 -> 12000
A7: 45814 | B7: =DAY(A7) -> 6 | C7: Port Harcourt | D7: Bola | E7: Beans | F7: Roots | G7: 17 | H7: 708 | I7: Customer_103 | J7: Female | K7: 500 | L7: =G7*H7 -> 12036 | M7: =dataset!$L7-T7 -> 3536 | N7: =dataset!$M7/dataset!$L7*100 -> 29.378531 | O7: =dataset!$K7*dataset!$G7 -> 8500 | T7: =dataset!$K7*dataset!$G7 -> 8500
A8: 45837 | B8: =DAY(A8) -> 29 | C8: Abuja | D8: Ade | E8: Bread | F8: Protein | G8: 25 | H8: 1859 | I8: Customer_104 | J8: Female | K8: 1250 | L8: =G8*H8 -> 46475 | M8: =dataset!$L8-T8 -> 15225 | N8: =dataset!$M8/dataset!$L8*100 -> 32.759548 | O8: =dataset!$K8*dataset!$G8 -> 31250 | T8: =dataset!$K8*dataset!$G8 -> 31250
A9: 45824 | B9: =DAY(A9) -> 16 | C9: Lagos | D9: Tunde | E9: Soap | F9: Grains | G9: 16 | H9: 2927 | I9: Customer_105 | J9: Female | K9: 2000 | L9: =G9*H9 -> 46832 | M9: =dataset!$L9-T9 -> 14832 | N9: =dataset!$M9/dataset!$L9*100 -> 31.670653 | O9: =dataset!$K9*dataset!$G9 -> 32000 | T9: =dataset!$K9*dataset!$G9 -> 32000
A10: 45827 | B10: =DAY(A10) -> 19 | C10: Ibadan | D10: John | E10: Rice | F10: Dairy | G10: 29 | H10: 911 | I10: Customer_106 | J10: Male | K10: 750 | L10: =G10*H10 -> 26419 | M10: =dataset!$L10-T10 -> 4669 | N10: =dataset!$M10/dataset!$L10*100 -> 17.672887 | O10: =dataset!$K10*dataset!$G10 -> 21750 | T10: =dataset!$K10*dataset!$G10 -> 21750
A11: 45779 | B11: =DAY(A11) -> 2 | C11: Lagos | D11: Bola | E11: Beans | F11: Protein | G11: 16 | H11: 2068 | I11: Customer_107 | J11: Female | K11: 1150 | L11: =G11*H11 -> 33088 | M11: =dataset!$L11-T11 -> 14688 | N11: =dataset!$M11/dataset!$L11*100 -> 44.390716 | O11: =dataset!$K11*dataset!$G11 -> 18400 | T11: =dataset!$K11*dataset!$G11 -> 18400
A12: 45832 | B12: =DAY(A12) -> 24 | C12: Lagos | D12: Ngozi | E12: Eggs | F12: Bakery | G12: 16 | H12: 403 | I12: Customer_108 | J12: Male | K12: 300 | L12: =G12*H12 -> 6448 | M12: =dataset!$L12-T12 -> 1648 | N12: =dataset!$M12/dataset!$L12*100 -> 25.558313 | O12: =dataset!$K12*dataset!$G12 -> 4800 | T12: =dataset!$K12*dataset!$G12 -> 4800
A13: 45831 | B13: =DAY(A13) -> 23 | C13: Lagos | D13: Ade | E13: Rice | F13: Protein | G13: 35 | H13: 1100 | I13: Customer_109 | J13: Male | K13: 750 | L13: =G13*H13 -> 38500 | M13: =dataset!$L13-T13 -> 12250 | N13: =dataset!$M13/dataset!$L13*100 -> 31.818182 | O13: =dataset!$K13*dataset!$G13 -> 26250 | T13: =dataset!$K13*dataset!$G13 -> 26250
A14: 45798 | B14: =DAY(A14) -> 21 | C14: Port Harcourt | D14: Chioma | E14: Eggs | F14: Protein | G14: 10 | H14: 2989 | I14: Customer_11 | J14: Female | K14: 2150 | L14: =G14*H14 -> 29890 | M14: =dataset!$L14-T14 -> 8390 | N14: =dataset!$M14/dataset!$L14*100 -> 28.069588 | O14: =dataset!$K14*dataset!$G14 -> 21500 | Q14: 122 | T14: =dataset!$K14*dataset!$G14 -> 21500
A15: 45749 | B15: =DAY(A15) -> 2 | C15: Port Harcourt | D15: John | E15: Eggs | F15: Household | G15: 5 | H15: 2899 | I15: Customer_110 | J15: Female | K15: 1900 | L15: =G15*H15 -> 14495 | M15: =dataset!$L15-T15 -> 4995 | N15: =dataset!$M15/dataset!$L15*100 -> 34.460159 | O15: =dataset!$K15*dataset!$G15 -> 9500 | P15: =MATCH("Customer_2",dataset!$I$2:$I$801,0) -> 112 | T15: =dataset!$K15*dataset!$G15 -> 9500
A16: 45780 | B16: =DAY(A16) -> 3 | C16: Kano | D16: Chioma | E16: Soap | F16: Snacks | G16: 50 | H16: 399 | I16: Customer_111 | J16: Male | K16: 300 | L16: =G16*H16 -> 19950 | M16: =dataset!$L16-T16 -> 4950 | N16: =dataset!$M16/dataset!$L16*100 -> 24.81203 | O16: =dataset!$K16*dataset!$G16 -> 15000 | T16: =dataset!$K16*dataset!$G16 -> 15000
A17: 45757 | B17: =DAY(A17) -> 10 | C17: Ibadan | D17: Ade | E17: Milk | F17: Roots | G17: 47 | H17: 2118 | I17: Customer_112 | J17: Female | K17: 1500 | L17: =G17*H17 -> 99546 | M17: =dataset!$L17-T17 -> 29046 | N17: =dataset!$M17/dataset!$L17*100 -> 29.17847 | O17: =dataset!$K17*dataset!$G17 -> 70500 | T17: =dataset!$K17*dataset!$G17 -> 70500
A18: 45801 | B18: =DAY(A18) -> 24 | C18: Abuja | D18: Ade | E18: Milk | F18: Dairy | G18: 14 | H18: 1826 | I18: Customer_113 | J18: Female | K18: 950 | L18: =G18*H18 -> 25564 | M18: =dataset!$L18-T18 -> 12264 | N18: =dataset!$M18/dataset!$L18*100 -> 47.973713 | O18: =dataset!$K18*dataset!$G18 -> 13300 | T18: =dataset!$K18*dataset!$G18 -> 13300
A19: 45763 | B19: =DAY(A19) -> 16 | C19: Port Harcourt | D19: Tunde | E19: Eggs | F19: Beverages | G19: 17 | H19: 2332 | I19: Customer_114 | J19: Male | K19: 1700 | L19: =G19*H19 -> 39644 | M19: =dataset!$L19-T19 -> 10744 | N19: =dataset!$M19/dataset!$L19*100 -> 27.101201 | O19: =dataset!$K19*dataset!$G19 -> 28900 | T19: =dataset!$K19*dataset!$G19 -> 28900
A20: 45770 | B20: =DAY(A20) -> 23 | C20: Lagos | D20: Fatima | E20: Soft Drink | F20: Protein | G20: 28 | H20: 2988 | I20: Customer_115 | J20: Female | K20: 1750 | L20: =G20*H20 -> 83664 | M20: =dataset!$L20-T20 -> 34664 | N20: =dataset!$M20/dataset!$L20*100 -> 41.432396 | O20: =dataset!$K20*dataset!$G20 -> 49000 | T20: =dataset!$K20*dataset!$G20 -> 49000
A21: 45828 | B21: =DAY(A21) -> 20 | C21: Lagos | D21: Bola | E21: Yam | F21: Snacks | G21: 20 | H21: 1597 | I21: Customer_116 | J21: Male | K21: 1250 | L21: =G21*H21 -> 31940 | M21: =dataset!$L21-T21 -> 6940 | N21: =dataset!$M21/dataset!$L21*100 -> 21.72824 | O21: =dataset!$K21*dataset!$G21 -> 25000 | T21: =dataset!$K21*dataset!$G21 -> 25000
A22: 45812 | B22: =DAY(A22) -> 4 | C22: Port Harcourt | D22: John | E22: Beans | F22: Bakery | G22: 7 | H22: 758 | I22: Customer_117 | J22: Female | K22: 450 | L22: =G22*H22 -> 5306 | M22: =dataset!$L22-T22 -> 2156 | N22: =dataset!$M22/dataset!$L22*100 -> 40.633245 | O22: =dataset!$K22*dataset!$G22 -> 3150 | T22: =dataset!$K22*dataset!$G22 -> 3150
A23: 45827 | B23: =DAY(A23) -> 19 | C23: Kano | D23: Tunde | E23: Plantain Chips | F23: Roots | G23: 26 | H23: 589 | I23: Customer_118 | J23: Male | K23: 450 | L23: =G23*H23 -> 15314 | M23: =dataset!$L23-T23 -> 3614 | N23: =dataset!$M23/dataset!$L23*100 -> 23.599321 | O23: =dataset!$K23*dataset!$G23 -> 11700 | T23: =dataset!$K23*dataset!$G23 -> 11700
A24: 45768 | B24: =DAY(A24) -> 21 | C24: Ibadan | D24: Bola | E24: Soap | F24: Snacks | G24: 36 | H24: 1892 | I24: Customer_119 | J24: Male | K24: 1400 | L24: =G24*H24 -> 68112 | M24: =dataset!$L24-T24 -> 17712 | N24: =dataset!$M24/dataset!$L24*100 -> 26.004228 | O24: =dataset!$K24*dataset!$G24 -> 50400 | T24: =dataset!$K24*dataset!$G24 -> 50400
A25: 45778 | B25: =DAY(A25) -> 1 | C25: Lagos | D25: Tunde | E25: Rice | F25: Spread | G25: 41 | H25: 1434 | I25: Customer_12 | J25: Female | K25: 1200 | L25: =G25*H25 -> 58794 | M25: =dataset!$L25-T25 -> 9594 | N25: =dataset!$M25/dataset!$L25*100 -> 16.317992 | O25: =dataset!$K25*dataset!$G25 -> 49200 | T25: =dataset!$K25*dataset!$G25 -> 49200
A26: 45778 | B26: =DAY(A26) -> 1 | C26: Ibadan | D26: Tunde | E26: Yam | F26: Bakery | G26: 16 | H26: 2075 | I26: Customer_120 | J26: Female | K26: 1800 | L26: =G26*H26 -> 33200 | M26: =dataset!$L26-T26 -> 4400 | N26: =dataset!$M26/dataset!$L26*100 -> 13.253012 | O26: =dataset!$K26*dataset!$G26 -> 28800 | T26: =dataset!$K26*dataset!$G26 -> 28800
A27: 45831 | B27: =DAY(A27) -> 23 | C27: Ibadan | D27: Fatima | E27: Butter | F27: Protein | G27: 38 | H27: 901 | I27: Customer_121 | J27: Male | K27: 750 | L27: =G27*H27 -> 34238 | M27: =dataset!$L27-T27 -> 5738 | N27: =dataset!$M27/dataset!$L27*100 -> 16.759156 | O27: =dataset!$K27*dataset!$G27 -> 28500 | T27: =dataset!$K27*dataset!$G27 -> 28500
... A801: 45805 | B801: =DAY(A801) -> 28 | C801: Abuja | D801: Ngozi | E801: Yam | F801: Snacks | G801: 35 | H801: 324 | I801: Customer_99 | J801: Male | K801: 200 | L801: =G801*H801 -> 11340 | M801: =dataset!$L801-T801 -> 4340 | N801: =dataset!$M801/dataset!$L801*100 -> 38.271605 | O801: =dataset!$K801*dataset!$G801 -> 7000 | T801: =dataset!$K801*dataset!$G801 -> 7000

Sheet Questions
A1: Student Questions
A2: 1. Calculate Total Sales for each transaction .
A3: 2. Which product had the highest unit price?
A4: 3. How many sales transactions were recorded in total?
A5: 4. How many customers are Male vs Female?
A6: 5. Which region recorded the most sales transactions?
A7: 6. What is the total sales revenue for each Product Category?
A8: 7. Which Salesperson made the highest sales in Q2 2025?
A9: 8. Show monthly sales totals for April, May, and June 2025.
A10: 9. What are the top 5 customers by sales value?
A11: 10. Compare average sales per transaction between Male vs Female customers.
A12: 11. Build a pivot table & chart showing sales by Region and Product Category. | B12: XX
A13: 12. Create a line chart showing daily sales trends across Q2 2025. | B13: XX
A14: 13. Which region bought the most Electronics products? | E14: xx no electronic products found
A15: 14. Calculate the average unit price of products in each category.
A16: 15. Build a dashboard with: Total Q2 Sales, Sales by Gender, Sales by Region, Top 5 Products, Monthly Trend.
A17: 16. Using the Cost Price column, calculate Profit for each transaction .
A18: 17. Which product category generates the highest total profit?
A19: 18. Which salesperson generated the highest profit overall?
A20: 19. Find the profit margin (%) for each product .
A21: 20. Identify the top 3 most profitable products.

Sheet pivot
B2: NUMBER 4
A3: Row Labels | B3: Count of Gender
A4: Female | B4: 385
A5: Male | B5: 415
L7: 164
X8: Row Labels | Y8: Sum of total sales
F9: Row Labels | G9: Sum of total sales | X9: Female | Y9: 17762638
F10: Lagos | G10: 7682927 | X10: Male | Y10: 18251437
C11: NUMBER 5 | F11: Port Harcourt | G11: 7629861 | X11: Grand Total | Y11: 36014075
B12: Row Labels | C12: Count of Region | F12: Abuja | G12: 7306128
B13: Port Harcourt | C13: 178 | F13: Ibadan | G13: 7147173 | S13: NUMBER 18
B14: Abuja | C14: 164 | F14: Kano | G14: 6247986 | R14: Row Labels | S14: Sum of PROFIT
B15: Ibadan | C15: 157 | R15: John | S15: 1553831
B16: Lagos | C16: 153 | R16: Bola | S16: 1500760
B17: Kano | C17: 148 | R17: Emeka | S17: 1337307
N18: Row Labels | O18: Sum of COST PRICE | R18: Chioma | S18: 1324683
N19: Bakery | O19: 2205150 | R19: Fatima | S19: 1276119
F20: NUMBER 6 | N20: Beverages | O20: 2331000 | R20: Ade | S20: 1269858
E21: Row Labels | F21: Sum of total sales | N21: Dairy | O21: 2988900 | R21: Ngozi | S21: 1217380
E22: Dairy | F22: 4393772 | N22: Grains | O22: 2544700 | R22: Tunde | S22: 1191687
E23: Protein | F23: 4275377 | I23: NUMBER 9 | N23: Household | O23: 2349150 | R23: Grand Total | S23: 10671625
C24: NUMBER 8 | E24: Snacks | F24: 4064541 | H24: Row Labels | I24: Sum of total sales | N24: Legumes | O24: 2314750 | S24: =GETPIVOTDATA("profit",$R$14) -> 10671625
B25: Row Labels | C25: Sum of total sales | E25: Grains | F25: 3816599 | H25: Customer_618 | I25: 142704 | N25: Protein | O25: 2975350
B26: Jun | C26: 12683091 | E26: Household | F26: 3445177 | H26: Customer_555 | I26: 141365 | N26: Roots | O26: 2249350
B27: Apr | C27: 12111948 | E27: Spread | F27: 3290000 | H27: Customer_624 | I27: 137690 | N27: Snacks | O27: 3059250
B28: May | C28: 11219036 | E28: Beverages | F28: 3266230 | H28: Customer_83 | I28: 136758 | N28: Spread | O28: 2324850
B29: Grand Total | C29: 36014075 | E29: Roots | F29: 3224090 | H29: Customer_588 | I29: 134504 | N29: Grand Total | O29: 25342450
E30: Legumes | F30: 3152526 | H30: Grand Total | I30: 693021 | O30: =GETPIVOTDATA("COST PRICE",$N$18) -> 25342450
E31: Bakery | F31: 3085763
E32: Grand Total | F32: 36014075
F33: =GETPIVOTDATA("total sales",$E$21) -> 36014075
M35: NUMBER 14 | P35: NUMBER 17
C36: NUMBER 10 | L36: Row Labels | M36: Average of Unit Price (NGN) | O36: Row Labels | P36: Sum of PROFIT | V36: NUMBER 12
B37: Row Labels | C37: Average of total sales | G37: NUMBER 11 | L37: Eggs | M37: 1746.8219 | O37: Dairy | P37: 1404872 | S37: Row Labels | T37: Sum of total sales | X37: Row Labels | Y37: Sum of total sales
B38: Female | C38: 46136.722 | F38: Row Labels | G38: Sum of total sales | L38: Bread | M38: 1713.1319 | O38: Protein | P38: 1300027 | S38: 01-Apr | T38: 382652 | X38: Bread | Y38: 4283769
B39: Male | C39: 43979.366 | F39: Lagos | G39: 7682927 | L39: Soft Drink | M39: 1697.5 | O39: Grains | P39: 1271899 | S39: 02-Apr | T39: 576316 | X39: Soap | Y39: 4080794
B40: Grand Total | C40: 45017.594 | F40: Bakery | G40: 498018 | L40: Milk | M40: 1680.0122 | O40: Household | P40: 1096027 | S40: 03-Apr | T40: 258419 | X40: Beans | Y40: 3885703
F41: Beverages | G41: 470761 | L41: Beans | M41: 1676.3133 | O41: Snacks | P41: 1005291 | S41: 04-Apr | T41: 330496 | X41: Milk | Y41: 3770944
F42: Dairy | G42: 1557049 | L42: Yam | M42: 1646.2375 | O42: Roots | P42: 974740 | S42: 05-Apr | T42: 493937 | X42: Plantain Chips | Y42: 3514986
F43: Grains | G43: 844959 | L43: Plantain Chips | M43: 1639.3514 | O43: Spread | P43: 965150 | S43: 06-Apr | T43: 240245 | X43: Yam | Y43: 3396761
F44: Household | G44: 582874 | L44: Rice | M44: 1596.9615 | O44: Beverages | P44: 935230 | S44: 07-Apr | T44: 330311 | X44: Eggs | Y44: 3385177
F45: Legumes | G45: 639483 | L45: Soap | M45: 1536.2737 | O45: Bakery | P45: 880613 | S45: 08-Apr | T45: 259972 | X45: Soft Drink | Y45: 3337385
F46: Protein | G46: 533521 | L46: Butter | M46: 1447.0541 | O46: Legumes | P46: 837776 | S46: 09-Apr | T46: 279530 | X46: Rice | Y46: 3205163
D47: NUMBER 19 | F47: Roots | G47: 1257148 | L47: Grand Total | M47: 1637.1688 | O47: Grand Total | P47: 10671625 | S47: 10-Apr | T47: 614736 | X47: Butter | Y47: 3153393
C48: Row Labels | D48: Average of PROFIT MARGIN | F48: Snacks | G48: 895697 | P48: =GETPIVOTDATA("profit",$O$36) -> 10671625 | S48: 11-Apr | T48: 113443 | X48: Grand Total | Y48: 36014075
C49: Beans | D49: 30.846926 | F49: Spread | G49: 403417 | S49: 12-Apr | T49: 406186
C50: Bread | D50: 29.485418 | F50: Port Harcourt | G50: 7629861 | S50: 13-Apr | T50: 309313
C51: Butter | D51: 29.162296 | F51: Bakery | G51: 747595 | S51: 14-Apr | T51: 369533
C52: Eggs | D52: 29.1636 | F52: Beverages | G52: 990106 | S52: 15-Apr | T52: 681126
C53: Milk | D53: 29.397068 | F53: Dairy | G53: 373047 | I53: NUMBER 7 | S53: 16-Apr | T53: 701727
C54: Plantain Chips | D54: 28.593296 | F54: Grains | G54: 1000566 | H54: Row Labels | I54: Sum of total sales | N54: NUMBER 20 | S54: 17-Apr | T54: 168643
C55: Rice | D55: 29.397243 | F55: Household | G55: 615727 | H55: John | I55: 5214581 | M55: Row Labels | N55: Sum of PROFIT | S55: 18-Apr | T55: 860954
C56: Soap | D56: 29.990141 | F56: Legumes | G56: 716303 | H56: Bola | I56: 4965010 | M56: Bread | N56: 1233069 | S56: 19-Apr | T56: 561610
C57: Soft Drink | D57: 30.750469 | F57: Protein | G57: 947891 | H57: Chioma | I57: 4533283 | M57: Beans | N57: 1191753 | S57: 20-Apr | T57: 334464
C58: Yam | D58: 28.78386 | F58: Roots | G58: 788128 | H58: Fatima | I58: 4375469 | M58: Soap | N58: 1170844 | S58: 21-Apr | T58: 602202
C59: Grand Total | D59: 29.567718 | F59: Snacks | G59: 773792 | H59: Emeka | I59: 4327807 | M59: Milk | N59: 1152544 | S59: 22-Apr | T59: 470792
F60: Spread | G60: 676706 | H60: Tunde | I60: 4259237 | M60: Soft Drink | N60: 1072235 | S60: 23-Apr | T60: 420970
F61: Abuja | G61: 7306128 | H61: Ngozi | I61: 4187580 | M61: Eggs | N61: 1048627 | S61: 24-Apr | T61: 260990
F62: Bakery | G62: 773611 | H62: Ade | I62: 4151108 | M62: Plantain Chips | N62: 1006636 | S62: 25-Apr | T62: 103489
F63: Beverages | G63: 413187 | H63: Grand Total | I63: 36014075 | M63: Yam | N63: 950911 | S63: 26-Apr | T63: 234109
F64: Dairy | G64: 978653 | M64: Rice | N64: 940213 | S64: 27-Apr | T64: 201817
F65: Grains | G65: 779458 | M65: Butter | N65: 904793 | S65: 28-Apr | T65: 676887
E66: NUMBER 2 | F66: Household | G66: 762989 | M66: Grand Total | N66: 10671625 | S66: 29-Apr | T66: 550935
D67: Row Labels | E67: Max of Unit Price (NGN) | F67: Legumes | G67: 572533 | S67: 30-Apr | T67: 316144
D68: Beans | E68: 2983 | F68: Protein | G68: 867074 | S68: 01-May | T68: 961628
D69: Rice | E69: 2992 | F69: Roots | G69: 412374 | S69: 02-May | T69: 320037
D70: Soap | E70: 2973 | F70: Snacks | G70: 668293 | S70: 03-May | T70: 203528
D71: Soft Drink | E71: 2988 | F71: Spread | G71: 1077956 | S71: 04-May | T71: 275465
D72: Yam | E72: 2898 | F72: Ibadan | G72: 7147173 | S72: 05-May | T72: 419943
D73: Bread | E73: 2989 | F73: Bakery | G73: 523179 | S73: 06-May | T73: 375945
D74: Butter | E74: 2950 | F74: Beverages | G74: 624947 | S74: 07-May | T74: 167281
D75: Eggs | E75: 2990 | F75: Dairy | G75: 898683 | S75: 08-May | T75: 445856
D76: Milk | E76: 2980 | F76: Grains | G76: 628057 | S76: 09-May | T76: 434070
D77: Plantain Chips | E77: 2958 | F77: Household | G77: 628384 | S77: 10-May | T77: 104782
D78: Grand Total | E78: 2992 | F78: Legumes | G78: 645698 | S78: 11-May | T78: 216926
F79: Protein | G79: 1110661 | S79: 12-May | T79: 188672
F80: Roots | G80: 454674 | S80: 13-May | T80: 519631
F81: Snacks | G81: 924635 | S81: 14-May | T81: 465612
F82: Spread | G82: 708255 | J82: product total sales | S82: 15-May | T82: 289672
F83: Kano | G83: 6247986 | I83: Row Labels | J83: Sum of total sales | S83: 16-May | T83: 148104
F84: Bakery | G84: 543360 | I84: Bread | J84: 4283769 | S84: 17-May | T84: 255912
F85: Beverages | G85: 767229 | I85: Soap | J85: 4080794 | S85: 18-May | T85: 382895
F86: Dairy | G86: 586340 | I86: Beans | J86: 3885703 | S86: 19-May | T86: 467347
F87: Grains | G87: 563559 | I87: Milk | J87: 3770944 | S87: 20-May | T87: 328703
F88: Household | G88: 855203 | I88: Plantain Chips | J88: 3514986 | P88: NUMBER 3 | S88: 21-May | T88: 353931
F89: Legumes | G89: 578509 | I89: Yam | J89: 3396761 | P89: Count of Customer Name | S89: 22-May | T89: 417047
F90: Protein | G90: 816230 | I90: Eggs | J90: 3385177 | P90: 800 | S90: 23-May | T90: 656151
F91: Roots | G91: 311766 | I91: Soft Drink | J91: 3337385 | S91: 24-May | T91: 352246
F92: Snacks | G92: 802124 | I92: Rice | J92: 3205163 | S92: 25-May | T92: 232624
F93: Spread | G93: 423666 | I93: Butter | J93: 3153393 | S93: 26-May | T93: 528271
F94: Grand Total | G94: 36014075 | I94: Grand Total | J94: 36014075 | S94: 27-May | T94: 495417
J95: =GETPIVOTDATA("total sales",$I$83) -> 36014075 | S95: 28-May | T95: 161492
S96: 29-May | T96: 507703
S97: 30-May | T97: 352662
S98: 31-May | T98: 189483
S99: 01-Jun | T99: 748640
S100: 02-Jun | T100: 206967
S101: 03-Jun | T101: 673421
S102: 04-Jun | T102: 463662
S103: 05-Jun | T103: 78942
...

Sheet dashboard

Sheet dashboard1

Sheet dashboard 2

Sheet dashboard 3 
